mtpy/__init__.py
mtpy/mtpy_globals.py
mtpy/analysis/__init__.py
mtpy/analysis/distortion.py
mtpy/analysis/doi.py
mtpy/analysis/geometry.py
mtpy/analysis/niblettbostick.py
mtpy/analysis/pt.py
mtpy/analysis/staticshift.py
mtpy/analysis/zinvariants.py
mtpy/contrib/__init__.py
mtpy/contrib/netcdf/__init__.py
mtpy/contrib/netcdf/modem_to_netCDF.py
mtpy/contrib/netcdf/nc.py
mtpy/contrib/netcdf/winglink_to_netCDF.py
mtpy/core/__init__.py
mtpy/core/edi.py
mtpy/core/edi_collection.py
mtpy/core/egbert.py
mtpy/core/jfile.py
mtpy/core/mt.py
mtpy/core/mt_xml.py
mtpy/core/ts.py
mtpy/core/z.py
mtpy/gui/__init__.py
mtpy/gui/convert_model_to_vtk.py
mtpy/gui/convert_model_to_vtk_qt5.py
mtpy/gui/edi_editor.py
mtpy/gui/edi_editor_qt5.py
mtpy/gui/get_edi_files.py
mtpy/gui/modem_mesh_builder.py
mtpy/gui/modem_model_manipulator.py
mtpy/gui/modem_model_manipulator_qt5.py
mtpy/gui/modem_plot_pt_maps.py
mtpy/gui/modem_plot_pt_maps_qt5.py
mtpy/gui/modem_plot_response.py
mtpy/gui/modem_plot_response_fast.py
mtpy/gui/modem_plot_response_faster.py
mtpy/gui/modem_plot_response_qt5.py
mtpy/gui/modem_plot_response_v2.py
mtpy/gui/mt_file_editor.py
mtpy/gui/my_stream.py
mtpy/gui/occam1d_gui.py
mtpy/gui/occam1d_gui_qt5.py
mtpy/gui/rotate_edi_files.py
mtpy/gui/rotate_edi_files_qt5.py
mtpy/gui/ws_plot_response.py
mtpy/imaging/__init__.py
mtpy/imaging/geology.py
mtpy/imaging/imaging_base.py
mtpy/imaging/mtcolors.py
mtpy/imaging/mtplot.py
mtpy/imaging/mtplottools.py
mtpy/imaging/penetration.py
mtpy/imaging/penetration_depth1d.py
mtpy/imaging/penetration_depth2d.py
mtpy/imaging/penetration_depth3d.py
mtpy/imaging/phase_tensor_maps.py
mtpy/imaging/phase_tensor_pseudosection.py
mtpy/imaging/plot_depth_slice.py
mtpy/imaging/plot_mt_response.py
mtpy/imaging/plot_resphase_maps.py
mtpy/imaging/plotnresponses.py
mtpy/imaging/plotpseudosection.py
mtpy/imaging/plotpt.py
mtpy/imaging/plotresidualptmaps.py
mtpy/imaging/plotresidualptps.py
mtpy-1.1.3.dist-info/METADATA
mtpy-1.1.3.dist-info/RECORD
mtpy-1.1.3.dist-info/WHEEL
mtpy-1.1.3.dist-info/entry_points.txt
mtpy-1.1.3.dist-info/top_level.txt
